./.gitignore
./PKG-INFO
./README.md
./__init__.py
./detect_text_in_image.py
./pyproject.toml
./test.py
feluda_detect_text_in_image_tesseract-0.1.1.dist-info/METADATA
feluda_detect_text_in_image_tesseract-0.1.1.dist-info/WHEEL
feluda_detect_text_in_image_tesseract-0.1.1.dist-info/RECORD
