Metadata-Version: 2.4
Name: feluda-detect-text-in-image-tesseract
Version: 0.1.1
Requires-Python: >=3.10
Requires-Dist: pillow>=11.1.0
Requires-Dist: pytesseract>=0.3.10
Requires-Dist: requests>=2.28.0
